{
  "gitSyncId": "6492e2637204916015a22d5b_64c9f541b82e614d8544c71b",
  "id": "Tagged Refunds by Create Date_Query2",
  "pluginId": "postgres-plugin",
  "pluginType": "DB",
  "unpublishedAction": {
    "actionConfiguration": {
      "body": "SELECT \"Payment\".\"amount\" as \"amount\", count(*) as count, \"amount\" * count(*) as  \"productRevenue\" FROM \"Payment\" where \"Payment\".\"createdAt\" >= {{moment(DatePicker1.selectedDate).format(\"YYYY-MM-DD\")}}::date - interval '330 minutes' and \"Payment\".\"createdAt\" <= {{moment(DatePicker2.selectedDate).format(\"YYYY-MM-DD\")}}::date + interval '1110 minutes' and \"status\" = 'responseReceivedRefund' and \"paymentForId\" = 3125 group by \"Payment\".\"amount\"\nunion\nSELECT null, count(*), sum(\"amount\") FROM \"Payment\" where  \"paymentForId\" = 3125 and \"createdAt\" >= {{moment(DatePicker1.selectedDate).format(\"YYYY-MM-DD\")}}::date - interval '330 minutes' and \"createdAt\" <= {{moment(DatePicker2.selectedDate).format(\"YYYY-MM-DD\")}}::date + interval '1110 minutes' and \"status\" = 'responseReceivedRefund' ORDER BY \"productRevenue\" desc;\n",
      "encodeParamsToggle": true,
      "paginationType": "NONE",
      "pluginSpecifiedTemplates": [
        {
          "value": true
        }
      ],
      "timeoutInMillisecond": 10000
    },
    "confirmBeforeExecute": false,
    "datasource": {
      "id": "learner1",
      "isAutoGenerated": false,
      "name": "learner1",
      "pluginId": "postgres-plugin"
    },
    "dynamicBindingPathList": [
      {
        "key": "body"
      }
    ],
    "name": "Query2",
    "pageId": "Tagged Refunds by Create Date",
    "runBehaviour": "ON_PAGE_LOAD",
    "userSetOnLoad": false
  }
}